logcheckerrdm/__init__.py
logcheckerrdm/common_rdm.py
logcheckerrdm/log_checker.py
logcheckerrdm/prepare_info.py
logcheckerRdm-0.0.1.dist-info/METADATA
logcheckerRdm-0.0.1.dist-info/WHEEL
logcheckerRdm-0.0.1.dist-info/top_level.txt
logcheckerRdm-0.0.1.dist-info/RECORD
